{
  "intents": [
    {
      "tag": "greeting_en",
      "patterns": [
        "Hi", "Hello", "Hey", "How are you?", "Good morning"
      ],
      "responses": [
        "Hi, how can I help you?", "Hello, how can I assist you?"
      ]
    },
    {
      "tag": "greeting_id",
      "patterns": [
        "Halo, bagaimana kabarmu?", "Selamat pagi, ada yang bisa saya bantu?",
        "Hai, senang bertemu denganmu!", "Apa kabar?", "Selamat datang, apa yang bisa saya bantu?"
      ],
      "responses": [
        "Hai, ada yang bisa saya bantu?", "Selamat datang di chatbot Era Beauty Care."
      ]
    },
    {
      "tag": "goodbye_en",
      "patterns": [
        "Bye", "See you later", "Goodbye", "Take care"
      ],
      "responses": [
        "Goodbye!", "See you soon!"
      ]
    },
    {
      "tag": "goodbye_id",
      "patterns": [
        "Sampai jumpa lagi!", "Selamat tinggal!", "Dadah!", "Sampai ketemu lagi!"
      ],
      "responses": [
        "Sampai jumpa lagi!"
      ]
    },
    {
      "tag": "thanks_en",
      "patterns": [
        "Thanks", "Thank you", "I appreciate it"
      ],
      "responses": [
        "You're welcome!", "No problem!"
      ]
    },
    {
      "tag": "thanks_id",
      "patterns": [
        "Terima kasih", "Saya sangat berterima kasih", "Makasih"
      ],
      "responses": [
        "Sama-sama!", "Tentu saja!"
      ]
    },
    {
      "tag": "apa_kabar",
      "patterns": [
        "Hai, apa kabar hari ini?", "Selamat pagi, bagaimana kabarmu?", "Apa kabar akhir-akhir ini?",
        "Halo, bagaimana perasaanmu?", "Assalamualaikum, bagaimana kabarmu?", "Hai, bagaimana harimu?"
      ],
      "responses": [
        "Hi, selamat datang! Apa yang bisa saya bantu?", "Halo, bagaimana kabarmu? Semoga baik-baik saja!"
      ]
    },
    {
      "tag": "tips_memilih_krim_pemutih_wajah",
      "patterns": [
        "Krim pemutih wajah", "Pemutih wajah", "Tips memilih krim wajah", 
        "Trik memilih krim pemutih", "Bagaimana memilih krim pemutih wajah?",
        "Saya butuh tips memilih pemutih wajah"
      ],
      "responses": [
        "1. Periksa bahan aktif seperti vitamin C atau arbutin.\n2. Hindari krim dengan bahan berbahaya seperti mercury.\n3. Pilih krim dengan SPF."
      ]
    },
    {
      "tag": "trik_merawat_kulit_berminyak",
      "patterns": [
        "Wajah berminyak", "Kulit berminyak", "Cara merawat kulit berminyak", 
        "Treatment untuk kulit berminyak", "Tips untuk kulit wajah berminyak"
      ],
      "responses": [
        "1. Gunakan pembersih wajah yang lembut.\n2. Gunakan pelembap berbasis gel.\n3. Gunakan masker lumpur seminggu sekali."
      ]
    },
    {
      "tag": "jerawat",
      "patterns": [
        "Jerawat", "Bagaimana cara mengatasi jerawat?", "Apa yang menyebabkan jerawat?", 
        "Tips untuk mencegah jerawat", "Apa yang memperburuk jerawat?", 
        "Bagaimana cara merawat jerawat?", "Cara menghilangkan jerawat batu"
      ],
      "responses": [
        "Jerawat disebabkan oleh hormon, minyak berlebih, dan pori-pori tersumbat. Gunakan produk dengan asam salisilat atau benzoyl peroxide."
      ]
    },
    {
      "tag": "jenis_kulit_berminyak",
      "patterns": [
        "Kulit saya cenderung berminyak.", "Saya punya kulit yang berminyak.", 
        "Jenis kulit saya berminyak.", "Wajah saya sering berminyak."
      ],
      "responses": [
        "Kulit berminyak disebabkan oleh produksi sebum yang berlebihan. Pastikan menggunakan produk yang cocok seperti salicylic acid."
      ]
    },
    {
      "tag": "jenis_kulit_kering",
      "patterns": [
        "Kulit saya cenderung kering.", "Saya memiliki kulit kering.", 
        "Jenis kulit saya kering.", "Kulit wajah saya sering kering."
      ],
      "responses": [
        "Kulit kering terjadi karena kurangnya produksi minyak alami. Gunakan produk pelembap seperti hyaluronic acid untuk menjaga kelembapan."
      ]
    },
    {
      "tag": "jenis_kulit_normal",
      "patterns": [
        "Kulit saya cenderung normal.", "Saya memiliki kulit normal.", 
        "Jenis kulit saya normal.", "Kulit wajah saya normal."
      ],
      "responses": [
        "Kulit normal memiliki keseimbangan antara kelembapan dan produksi minyak. Gunakan produk pelembap ringan dan lindungi kulit dari sinar UV."
      ]
    },
    {
      "tag": "jenis_kulit_kombinasi",
      "patterns": [
        "Kulit saya kombinasi.", "Saya punya kulit kombinasi.", 
        "Jenis kulit saya kombinasi.", "Wajah saya kadang kering, kadang berminyak."
      ],
      "responses": [
        "Kulit kombinasi biasanya berminyak di area T-zone dan kering di area pipi. Gunakan produk yang sesuai dengan kedua kondisi ini, seperti pelembap non-komedogenik."
      ]
    },
    {
      "tag": "jenis_kulit_sensitif",
      "patterns": [
        "Kulit saya sensitif.", "Saya punya kulit yang sensitif.", 
        "Kulit saya sering iritasi.", "Kulit wajah saya rentan kemerahan."
      ],
      "responses": [
        "Kulit sensitif mudah bereaksi terhadap produk atau lingkungan. Gunakan produk yang lembut dan bebas wewangian, seperti yang mengandung chamomile atau aloe vera."
      ]
    }
  ]
}
